bulksms/__init__.py
bulksms/admin.py
bulksms/apps.py
bulksms/errors.py
bulksms/models.py
bulksms/settings.py
bulksms/settings_test.py
bulksms/sms.py
bulksms/utils.py
django_bulksms-0.0.1.dist-info/DESCRIPTION.rst
django_bulksms-0.0.1.dist-info/METADATA
django_bulksms-0.0.1.dist-info/RECORD
django_bulksms-0.0.1.dist-info/WHEEL
django_bulksms-0.0.1.dist-info/metadata.json
django_bulksms-0.0.1.dist-info/top_level.txt
