Metadata-Version: 2.0
Name: django-bulksms
Version: 0.0.1
Summary: Django BulkSMS library/API.
Home-page: https://github.com/tsotetsi/django-bulksms
Author: Thapelo Tsotetsi
Author-email: info@thapelotsotetsi.co.za
License: MIT
Keywords: django bulk sms sending
Platform: UNKNOWN
Classifier: Programming Language :: Python
Classifier: Topic :: Software Development :: Libraries :: Python Modules
Classifier: License :: OSI Approved :: MIT License
Classifier: Environment :: Web Environment
Classifier: Development Status :: 3 - Alpha
Classifier: Intended Audience :: Developers
Classifier: Programming Language :: Python :: 2.6
Classifier: Programming Language :: Python :: 2.7
Classifier: Programming Language :: Python :: 3.2
Classifier: Programming Language :: Python :: 3.4
Classifier: Programming Language :: Python :: 3.5
Classifier: Programming Language :: Python
Classifier: Framework :: Django
Classifier: Framework :: Django :: 1.5
Classifier: Framework :: Django :: 1.6
Classifier: Framework :: Django :: 1.7
Classifier: Framework :: Django :: 1.8
Classifier: Framework :: Django :: 1.9
Classifier: Framework :: Django :: 1.10
Requires-Dist: Django
Requires-Dist: requests
Requires-Dist: phonenumbers
Requires-Dist: tenacity
